tg_searcher-0.5.0.dist-info/METADATA
tg_searcher-0.5.0.dist-info/WHEEL
tg_searcher-0.5.0.dist-info/entry_points.txt
tg_searcher-0.5.0.dist-info/licenses/LICENSE
tg_searcher/__init__.py
tg_searcher/__main__.py
tg_searcher/backend_bot.py
tg_searcher/common.py
tg_searcher/frontend_bot.py
tg_searcher/indexer.py
tg_searcher/main.py
tg_searcher/session.py
tg_searcher-0.5.0.dist-info/RECORD
