Metadata-Version: 2.1
Name: tg-searcher
Version: 0.5.0
Summary: Telegram searcher bot for Chinese
Home-page: https://github.com/SharzyL/tg_searcher
Author-Email: SharzyL <me@sharzy.in>
License: MIT
Classifier: Development Status :: 3 - Alpha
Classifier: License :: OSI Approved :: MIT License
Classifier: Intended Audience :: Developers
Classifier: Intended Audience :: End Users/Desktop
Classifier: Programming Language :: Python :: 3 :: Only
Classifier: Programming Language :: Python :: 3.9
Classifier: Topic :: Communications :: Chat
Classifier: Topic :: Utilities
Project-URL: Changelog, https://github.com/SharzyL/tg_searcher/blob/master/CHANGELOG.md
Project-URL: Homepage, https://github.com/SharzyL/tg_searcher
Project-URL: Repository, https://github.com/SharzyL/tg_searcher.git
Requires-Python: <4.0,>=3.9
Requires-Dist: Telethon<2.0.0,>=1.32.0
Requires-Dist: python-socks<3.0.0,>=2.4.4
Requires-Dist: cryptg<1.0.0,>=0.4.0
Requires-Dist: async-timeout<5.0.0,>=4.0.3
Requires-Dist: jieba>=0.42.1
Requires-Dist: pyyaml>=6.0.1
Requires-Dist: redis>=5.0.3
Requires-Dist: whoosh>=2.7.4
